metallic/__init__.py
metallic/version.py
metallic/data/__init__.py
metallic/data/dataloader.py
metallic/data/sampler.py
metallic/data/_utils/__init__.py
metallic/data/_utils/collate.py
metallic/data/_utils/splits.py
metallic/data/benchmarks/__init__.py
metallic/data/benchmarks/miniimagenet.py
metallic/data/benchmarks/omniglot.py
metallic/data/datasets/__init__.py
metallic/data/datasets/base.py
metallic/data/datasets/miniimagenet.py
metallic/data/datasets/omniglot.py
metallic/data/transforms/__init__.py
metallic/data/transforms/_utils.py
metallic/data/transforms/categorical.py
metallic/data/transforms/hflip.py
metallic/data/transforms/rotation.py
metallic/data/transforms/vflip.py
metallic/metalearners/__init__.py
metallic/metalearners/gbml.py
metallic/metalearners/maml.py
metallic/models/__init__.py
metallic/models/base.py
metallic/models/cnn.py
metallic/models/mlp.py
metallic/trainer/__init__.py
metallic/trainer/gbml.py
metallic/utils/__init__.py
metallic/utils/metrics.py
metallic-0.1.0.dist-info/LICENSE
metallic-0.1.0.dist-info/METADATA
metallic-0.1.0.dist-info/WHEEL
metallic-0.1.0.dist-info/top_level.txt
metallic-0.1.0.dist-info/RECORD
