Metadata-Version: 2.1
Name: metallic
Version: 0.1.0
Summary: A simple toolbox for meta-learning research based on Pytorch.
Home-page: https://github.com/Renovamen/metallic
Author: Xiaohan Zou
Author-email: renovamenzxh@gmail.com
License: MIT
Platform: UNKNOWN
Requires-Dist: numpy (<1.20.0,>=1.14.0)
Requires-Dist: torch (>=1.4.0)
Requires-Dist: torchvision (>=0.5.0)
Requires-Dist: higher (>=0.2.1)
Requires-Dist: requests
Requires-Dist: tqdm
